heflow/__init__.py
heflow/codecs.py
heflow/contexts.py
heflow/keys.py
heflow/models.py
heflow/tensors.py
heflow/cli/__init__.py
heflow/cli/keygen.py
heflow/plugins/__init__.py
heflow/plugins/contexts.py
heflow/plugins/keys.py
heflow/sklearn/__init__.py
heflow/sklearn/linear_model.py
heflow/tensorflow/__init__.py
heflow/tensorflow/keras/__init__.py
heflow/tensorflow/keras/activations.py
heflow/ui/__init__.py
heflow-1.5.0.dist-info/LICENSE
heflow-1.5.0.dist-info/METADATA
heflow-1.5.0.dist-info/NOTICE
heflow-1.5.0.dist-info/WHEEL
heflow-1.5.0.dist-info/entry_points.txt
heflow-1.5.0.dist-info/top_level.txt
heflow-1.5.0.dist-info/RECORD
