Metadata-Version: 2.1
Name: heflow
Version: 1.5.0
Summary: HEflow: A platform for the privacy-preserving machine learning lifecycle
Home-page: https://github.com/inaccel/heflow
Author: InAccel
Author-email: info@inaccel.com
License: Apache-2.0
Platform: Linux
Classifier: Development Status :: 5 - Production/Stable
Classifier: License :: OSI Approved :: Apache Software License
Classifier: Operating System :: POSIX :: Linux
Classifier: Programming Language :: Python
Classifier: Programming Language :: Python :: 3
Classifier: Programming Language :: Python :: 3.8
Classifier: Programming Language :: Python :: 3.9
Classifier: Programming Language :: Python :: 3.10
Requires-Python: >=3.8
License-File: LICENSE
License-File: NOTICE
Requires-Dist: mlflow[extras] ==2.6.0
Requires-Dist: tenseal ==0.3.14
Requires-Dist: tqdm
Provides-Extra: extras
Requires-Dist: psycopg2 ; extra == 'extras'
